nonebot/adapters/milky/__init__.py
nonebot/adapters/milky/adapter.py
nonebot/adapters/milky/bot.py
nonebot/adapters/milky/config.py
nonebot/adapters/milky/event.py
nonebot/adapters/milky/exception.py
nonebot/adapters/milky/message.py
nonebot/adapters/milky/model/__init__.py
nonebot/adapters/milky/model/api.py
nonebot/adapters/milky/model/base.py
nonebot/adapters/milky/model/common.py
nonebot/adapters/milky/model/message.py
nonebot/adapters/milky/permission.py
nonebot/adapters/milky/utils.py
nonebot_adapter_milky-1.0.0.dist-info/METADATA
nonebot_adapter_milky-1.0.0.dist-info/WHEEL
nonebot_adapter_milky-1.0.0.dist-info/entry_points.txt
nonebot_adapter_milky-1.0.0.dist-info/licenses/LICENSE
nonebot_adapter_milky-1.0.0.dist-info/RECORD
