Metadata-Version: 2.1
Name: nonebot-adapter-milky
Version: 1.0.0
Summary: Nonebot Adapter of Milky Protocol
Author-Email: RF-Tar-Railt <rf_tar_railt@qq.com>
License: MIT
Requires-Python: >=3.10
Requires-Dist: nonebot2>=2.4.2
